sciunit/__init__.py
sciunit/__main__.py
sciunit/base.py
sciunit/capabilities.py
sciunit/converters.py
sciunit/errors.py
sciunit/suites.py
sciunit/tests.py
sciunit/utils.py
sciunit/validators.py
sciunit/models/__init__.py
sciunit/models/backends.py
sciunit/models/base.py
sciunit/models/examples.py
sciunit/models/runnable.py
sciunit/scores/__init__.py
sciunit/scores/base.py
sciunit/scores/collections.py
sciunit/scores/collections_m2m.py
sciunit/scores/complete.py
sciunit/scores/incomplete.py
sciunit/unit_test/__init__.py
sciunit/unit_test/__main__.py
sciunit/unit_test/active.py
sciunit/unit_test/backend_tests.py
sciunit/unit_test/base.py
sciunit/unit_test/base_tests.py
sciunit/unit_test/command_line_tests.py
sciunit/unit_test/config_tests.py
sciunit/unit_test/converter_tests.py
sciunit/unit_test/doc_tests.py
sciunit/unit_test/error_tests.py
sciunit/unit_test/import_tests.py
sciunit/unit_test/model_tests.py
sciunit/unit_test/observation_tests.py
sciunit/unit_test/score_tests.py
sciunit/unit_test/test_tests.py
sciunit/unit_test/utils_tests.py
sciunit/unit_test/validator_tests.py
sciunit-0.2.7.dist-info/LICENSE
sciunit-0.2.7.dist-info/METADATA
sciunit-0.2.7.dist-info/WHEEL
sciunit-0.2.7.dist-info/entry_points.txt
sciunit-0.2.7.dist-info/top_level.txt
sciunit-0.2.7.dist-info/RECORD
