Metadata-Version: 2.1
Name: sciunit
Version: 0.2.7
Summary: A test-driven framework for formally validating scientific models against data.
Home-page: http://sciunit.scidash.org
Author: Rick Gerkin
Author-email: rgerkin@asu.edu
License: MIT
Platform: UNKNOWN
Classifier: License :: OSI Approved :: MIT License
Classifier: Programming Language :: Python :: 3
Classifier: Programming Language :: Python :: 3.7
Classifier: Programming Language :: Python :: 3.8
Classifier: Programming Language :: Python :: 3.9
Requires-Python: >=3.7
License-File: LICENSE
Requires-Dist: bs4
Requires-Dist: cerberus (>=1.2)
Requires-Dist: deepdiff
Requires-Dist: gitpython
Requires-Dist: importlib-metadata (<4.0)
Requires-Dist: ipykernel
Requires-Dist: ipython
Requires-Dist: jsonpickle
Requires-Dist: lxml
Requires-Dist: matplotlib
Requires-Dist: nbconvert
Requires-Dist: nbformat
Requires-Dist: pandas (>=0.18)
Requires-Dist: quantities (>=0.13.0)
